trace_scraper/__init__.py
trace_scraper/cli.py
trace_scraper/html_utils.py
trace_scraper/models.py
trace_scraper/py.typed
trace_scraper/scraper.py
trace_scraper/sitemap.py
trace_scraper-1.0.0.dist-info/METADATA
trace_scraper-1.0.0.dist-info/WHEEL
trace_scraper-1.0.0.dist-info/entry_points.txt
trace_scraper-1.0.0.dist-info/licenses/LICENSE
trace_scraper-1.0.0.dist-info/RECORD
