Metadata-Version: 2.4
Name: trace-scraper
Version: 1.0.0
Summary: High-performance async web scraper with Playwright and httpx. Scrape JavaScript-rendered pages, crawl websites recursively, parse sitemaps, and extract content with anti-bot bypass.
Project-URL: Homepage, https://github.com/boxed-dev/trace
Project-URL: Documentation, https://github.com/boxed-dev/trace#readme
Project-URL: Repository, https://github.com/boxed-dev/trace
Project-URL: Issues, https://github.com/boxed-dev/trace/issues
Project-URL: Changelog, https://github.com/boxed-dev/trace/releases
Author-email: Rishabh <rishabh@lumiora.co>
License-Expression: MIT
License-File: LICENSE
Keywords: anti-bot,async,asyncio,beautifulsoup,content-extraction,crawler,data-extraction,headless-browser,html-parser,httpx,javascript-rendering,pdf-extraction,playwright,rate-limiting,scraper,scraping,sitemap,sitemap-parser,spider,web-crawler,web-scraper,web-scraping
Classifier: Development Status :: 5 - Production/Stable
Classifier: Environment :: Console
Classifier: Framework :: AsyncIO
Classifier: Intended Audience :: Developers
Classifier: Intended Audience :: Information Technology
Classifier: Intended Audience :: Science/Research
Classifier: License :: OSI Approved :: MIT License
Classifier: Natural Language :: English
Classifier: Operating System :: OS Independent
Classifier: Programming Language :: Python :: 3
Classifier: Programming Language :: Python :: 3 :: Only
Classifier: Programming Language :: Python :: 3.11
Classifier: Programming Language :: Python :: 3.12
Classifier: Programming Language :: Python :: 3.13
Classifier: Topic :: Internet :: WWW/HTTP
Classifier: Topic :: Internet :: WWW/HTTP :: Indexing/Search
Classifier: Topic :: Internet :: WWW/HTTP :: Site Management :: Link Checking
Classifier: Topic :: Software Development :: Libraries :: Python Modules
Classifier: Topic :: Text Processing :: Markup :: HTML
Classifier: Typing :: Typed
Requires-Python: >=3.11
Requires-Dist: beautifulsoup4>=4.12.0
Requires-Dist: httpx>=0.25.0
Requires-Dist: lxml>=4.9.0
Requires-Dist: playwright>=1.40.0
Provides-Extra: all
Requires-Dist: pypdf>=3.17.0; extra == 'all'
Provides-Extra: dev
Requires-Dist: mypy>=1.7.0; extra == 'dev'
Requires-Dist: pytest-asyncio>=0.21.0; extra == 'dev'
Requires-Dist: pytest>=7.4.0; extra == 'dev'
Requires-Dist: ruff>=0.1.0; extra == 'dev'
Provides-Extra: pdf
Requires-Dist: pypdf>=3.17.0; extra == 'pdf'
